MANIFEST.in
README.md
setup.py
simple/__init__.py
simple/PIL/__init__.py
simple/PIL/image.py
simple_packages.egg-info/PKG-INFO
simple_packages.egg-info/SOURCES.txt
simple_packages.egg-info/dependency_links.txt
simple_packages.egg-info/requires.txt
simple_packages.egg-info/top_level.txt