Metadata-Version: 1.1
Name: simple-packages
Version: 0.1.2
Summary: Simple, consistent APIs for popular Python packages.
Home-page: https://github.com/groklearning/simple-packages
Author: Grok Learning
Author-email: opensource@groklearning.com
License: MIT
Platform: UNKNOWN
Classifier: Development Status :: 3 - Alpha
Classifier: License :: OSI Approved :: MIT License
Classifier: Natural Language :: English
Classifier: Programming Language :: Python
Classifier: Programming Language :: Python :: 3
Classifier: Programming Language :: Python :: 3.3
Classifier: Programming Language :: Python :: 3.4
Classifier: Programming Language :: Python :: 3.5
